flask_restplus_data/FlaskDataRepository.py
flask_restplus_data/__init__.py
flask_restplus_data/database.py
flask_restplus_data/enum.py
flask_restplus_data/resources/__init__.py
tests/__init__.py
tests/test_SQLRepository.py
tests/test_database.py
tests/resources/__init__.py
tests/resources/test_migrations/__init__.py
tests/resources/test_migrations/mongodb_migrations/1_init.py
tests/resources/test_migrations/mongodb_migrations/__init__.py
tests/resources/test_migrations/postgres_migrations/V1_1__init.py
tests/resources/test_migrations/postgres_migrations/__init__.py
flask_restplus_data-0.0.8.dist-info/LICENSE
flask_restplus_data-0.0.8.dist-info/METADATA
flask_restplus_data-0.0.8.dist-info/WHEEL
flask_restplus_data-0.0.8.dist-info/top_level.txt
flask_restplus_data-0.0.8.dist-info/RECORD
