Metadata-Version: 2.1
Name: flask-restplus-data
Version: 0.0.8
Summary: Library inspired by Spring Data to perform Operations on datastores
Home-page: https://github.com/nucklehead/flask-restplus-data
Author: nucklehead
Author-email: pierevans@gmail.com
License: MIT
Download-URL: https://github.com/nucklehead/flask-restplus-data/tarball/0.0.8
Keywords: datastore,sql,nosql,postgres,mysql,sqlite,obdc,oracle database,mongodb,orm,flask,flask_restplus,rest,restplus
Platform: UNKNOWN
Classifier: Development Status :: 3 - Alpha
Classifier: Intended Audience :: Developers
Classifier: Topic :: Software Development
Classifier: Framework :: Flask
Classifier: License :: OSI Approved :: MIT License
Classifier: Programming Language :: Python :: 3.6
Classifier: Programming Language :: Python :: 3.7
Classifier: Programming Language :: Python :: 3.8
Requires-Dist: confuse (==1.0.0)
Requires-Dist: psycopg2-binary (==2.8.6)
Requires-Dist: flask-sqlalchemy (==2.4.1)
Requires-Dist: Flask-MongoAlchemy (==0.7.2)
Requires-Dist: yoyo-migrations (==6.1.0)
Requires-Dist: mongodb-migrations (==0.7.0)
